BeautifulSauce/__init__.py
BeautifulSauce/css_attrs.csv
BeautifulSauce/featurizer.py
BeautifulSauce/sauce.py
BeautifulSauce-0.0.8.dist-info/METADATA
BeautifulSauce-0.0.8.dist-info/RECORD
BeautifulSauce-0.0.8.dist-info/WHEEL
BeautifulSauce-0.0.8.dist-info/top_level.txt
tests/__init__.py
tests/test_featurizer.py
tests/test_sauce.py
